{
    "base_datos" : [
        {
            "id": 1,
            "Nombre": 	  "Nicolás Fuentes",
            "Puesto": 	  "Director General, El Mago del Marketing",
            "Antiguedad": "Co-Fundador e Ideologo",
            "imagen": "https://p1.pxfuel.com/preview/715/820/938/face-high-contrast-black-and-white-bearded-man.jpg"
        },

        {
            "id": 2,
            "Nombre": 	  "Maximiliano Jatib",
            "Puesto": 	  "Gerente de Diseño, El Cerebro de todo esto",
            "Antiguedad": "Co-Fundador y Alma Mater",
            "imagen": "https://p1.pxfuel.com/preview/435/654/533/beard-face-man-model.jpg"

        },

        {
            "id": 3,
            "Nombre": 	  "Xavier Prado",
            "Puesto": 	  "Jefe de Proyecto, en algo había que ponerlo...",
            "Antiguedad": "5 semananas y contando...",
            "imagen": "https://p0.pxfuel.com/preview/367/949/231/human-man-mr-male.jpg"
        }
    ],
    "profile": {
        "name": "Xavi1982"
    }
}
